ComPDFKitConversion.cp310-win_amd64.pyd
ComPDFKitConversion.pyi
DocumentAI.dll
cpdfconversionsdk.dll
onnxruntime.dll
onnxruntime_providers_shared.dll
opencv_world4100.dll
opencv_world480.dll
compdfkitconversion-3.1.0.dist-info/METADATA
compdfkitconversion-3.1.0.dist-info/WHEEL
compdfkitconversion-3.1.0.dist-info/top_level.txt
compdfkitconversion-3.1.0.dist-info/RECORD
