Metadata-Version: 2.4
Name: ComPDFKitConversion
Version: 3.1.0
Summary: ComPDFKit Conversion Python SDK
Home-page: https://www.compdf.com
Author: PDF Technologies, Inc.
Author-email: support@compdf.com
Classifier: Programming Language :: Python :: 3.10
Classifier: Operating System :: Microsoft :: Windows
Classifier: Intended Audience :: Developers
Requires-Python: >=3.6
Dynamic: author
Dynamic: author-email
Dynamic: classifier
Dynamic: description
Dynamic: description-content-type
Dynamic: home-page
Dynamic: requires-python
Dynamic: summary
